pyfolioclient/__init__.py
pyfolioclient/__version__.py
pyfolioclient/_decorators.py
pyfolioclient/_exceptions.py
pyfolioclient/foliobaseclient.py
pyfolioclient/folioclient.py
pyfolioclient/py.typed
pyfolioclient-0.1.7.dist-info/METADATA
pyfolioclient-0.1.7.dist-info/WHEEL
pyfolioclient-0.1.7.dist-info/licenses/LICENSE
pyfolioclient-0.1.7.dist-info/RECORD
