Metadata-Version: 2.4
Name: pyfolioclient
Version: 0.1.7
Summary: A Python client for interacting with FOLIO's APIs.
Project-URL: Homepage, https://github.com/balljok/pyfolioclient
Project-URL: Issues, https://github.com/balljok/pyfolioclient/issues
Author-email: Håkan Sundblad <hakan.sundblad@liu.se>
License-Expression: MIT
License-File: LICENSE
Classifier: Development Status :: 3 - Alpha
Classifier: Intended Audience :: Developers
Classifier: License :: OSI Approved :: MIT License
Classifier: Operating System :: OS Independent
Classifier: Programming Language :: Python :: 3.9
Classifier: Programming Language :: Python :: 3.10
Classifier: Programming Language :: Python :: 3.11
Classifier: Programming Language :: Python :: 3.12
Classifier: Programming Language :: Python :: 3.13
Classifier: Topic :: Internet :: WWW/HTTP
Classifier: Topic :: Software Development :: Libraries :: Python Modules
Classifier: Typing :: Typed
Requires-Python: >=3.9
Requires-Dist: httpx>=0.28.1
